gflight.py
gflight_api-0.0.1.dist-info/LICENSE
gflight_api-0.0.1.dist-info/METADATA
gflight_api-0.0.1.dist-info/WHEEL
gflight_api-0.0.1.dist-info/top_level.txt
gflight_api-0.0.1.dist-info/RECORD
